tgext.celery-0.1.2-py3.10-nspkg.pth
tgext/celery/__init__.py
tgext/celery/celery.py
tgext/celery/commands.py
tgext.celery-0.1.2.dist-info/LICENSE
tgext.celery-0.1.2.dist-info/METADATA
tgext.celery-0.1.2.dist-info/WHEEL
tgext.celery-0.1.2.dist-info/entry_points.txt
tgext.celery-0.1.2.dist-info/namespace_packages.txt
tgext.celery-0.1.2.dist-info/top_level.txt
tgext.celery-0.1.2.dist-info/RECORD
