Metadata-Version: 2.1
Name: tgext.celery
Version: 0.1.2
Summary: UNKNOWN
Home-page: https://github.com/axant/tgext.celery.git
Author: Vincenzo Castiglia
Author-email: vincenzo.castiglia@axant.it
License: MIT
Keywords: turbogears2.extension
Platform: UNKNOWN
License-File: LICENSE
Requires-Dist: TurboGears2 (>=2.3.11)
Requires-Dist: gearbox
Requires-Dist: PasteDeploy
Requires-Dist: celery[mongodb]
Requires-Dist: threadpool
